cv_timeseries/__init__.py
cv_timeseries/plots/__init__.py
cv_timeseries/plots/plot_cv.py
cv_timeseries/statistics/__init__.py
cv_timeseries/statistics/calculate_cv.py
cv_timeseries-0.0.2.dist-info/METADATA
cv_timeseries-0.0.2.dist-info/WHEEL
cv_timeseries-0.0.2.dist-info/top_level.txt
cv_timeseries-0.0.2.dist-info/RECORD
