Metadata-Version: 2.1
Name: cv-timeseries
Version: 0.0.2
Summary: My short description
Home-page: https://github.com/anasofiama/package_creation.git
Author: Ana
Author-email: sofia.mirandaalbuquerque@gmail.com
Requires-Python: >=3.8
Requires-Dist: numpy
Requires-Dist: matplotlib
